[{"id": "3z8h0TU7ReDPLIbEnYhWZb", "name": "Bohemian Rhapsody", "artists": "Queen"}, {"id": "5T8EDUDqKcs6OSOwEsfqG7", "name": "Don't Stop Me Now - Remastered 2011", "artists": "Queen"}, {"id": "5txoZyuAmtCfmDjUCEphWm", "name": "Somebody To Love", "artists": "Queen"}, {"id": "300YN8ebGB90nDuzgz0f3O", "name": "Killer Queen", "artists": "Queen"}, {"id": "2fuCquhmrzHpu5xcA1ci9x", "name": "Under Pressure - Remastered 2011", "artists": "Queen, David Bowie"}, {"id": "6suU8oBlW4O2pg88tOXgHo", "name": "Under Pressure", "artists": "Queen, David Bowie"}, {"id": "3INsYP1Y8GG4qJvBsKCdXC", "name": "Don't Stop Me Now - ...Revisited", "artists": "Queen"}, {"id": "5WZDLZVCvY1rEyNir6k8Pg", "name": "The Show Must Go On", "artists": "Queen"}, {"id": "4cIPLtg1avt2Jm3ne9S1zy", "name": "Killer Queen - Remastered 2011", "artists": "Queen"}, {"id": "0GjEhVFGZW8afUYGChu3Rr", "name": "Dancing Queen", "artists": "ABBA"}]